[
    {"input": "你 好", "output": "你好！"},
    {"input": "你好", "output": "你好！"},
    {"input": "谢谢", "output": "谢谢！"},
    {"input": "对不起", "output": "对不起。"},
    {"input": "没关系", "output": "没关系。"},
    {"input": "为什么", "output": "为什么？"},
    {"input": "谁", "output": "谁？"},
    {"input": "谁 你", "output": "你是谁？"},
    {"input": "我 你 喜欢", "output": "我喜欢你。"},
    {"input": "喜欢 我 你", "output": "我喜欢你。"},
    {"input": "你 喜欢 我", "output": "你喜欢我吗？"},
    {"input": "我 大家 喜欢", "output": "我喜欢大家。"},
    {"input": "喜欢 手语 我", "output": "我喜欢手语。"},
    {"input": "你 手语 会", "output": "你会手语吗？"},
    {"input": "会 手语 我", "output": "我会手语。"},
    {"input": "会 我 手语", "output": "我会手语。"},
    {"input": "谢谢 你", "output": "谢谢你。"},
    {"input": "你 谢谢", "output": "谢谢你。"},
    {"input": "谢谢 大家", "output": "谢谢大家！"},
    {"input": "大家 谢谢", "output": "谢谢大家！"},
    {"input": "你 对不起", "output": "对不起。"},
    {"input": "对不起 我 你", "output": "我对不起你。"},
    {"input": "你 没关系", "output": "没关系。"},
    {"input": "为什么 你 喜欢 我", "output": "你为什么喜欢我？"},
    {"input": "喜欢 你 我 为什么", "output": "你为什么喜欢我？"},
    {"input": "为什么 对不起 你", "output": "你为什么要说对不起？"},
    {"input": "对不起 为什么 你", "output": "你为什么要说对不起？"},
    {"input": "谁 喜欢 手语", "output": "谁喜欢手语？"},
    {"input": "手语 谁 喜欢", "output": "谁喜欢手语？"},
    {"input": "谁 会 手语", "output": "谁会手语？"},
    {"input": "手语 会 谁", "output": "谁会手语？"},
    {"input": "手语 你 会 为什么", "output": "你为什么会手语？"},
    {"input": "为什么 会 你 手语", "output": "你为什么会手语？"},
    {"input": "你好 谢谢", "output": "你好，谢谢！"},
    {"input": "你好 大家", "output": "大家好！"},
    {"input": "你好 我 大家 喜欢", "output": "大家好，我喜欢你们。"},
    {"input": "你好 我 喜欢 手语", "output": "你好，我喜欢手语。"},
    {"input": "你好 我 会 手语", "output": "你好，我会手语。"},
    {"input": "你好 你 会 手语", "output": "你好，你会手语吗？"},
    {"input": "对不起 没关系", "output": "对不起，没关系。"},
    {"input": "没关系 对不起", "output": "对不起，没关系。"},
    {"input": "谢谢 没关系", "output": "谢谢，没关系。"},
    {"input": "你好 喜欢 你 我", "output": "你好，我喜欢你。"},
    {"input": "我 你 喜欢 手语 会", "output": "我喜欢你，你会手语吗？"},
    {"input": "喜欢 你 手语 会 我", "output": "我喜欢你，我会手语。"},
    {"input": "为什么 喜欢 手语 你", "output": "你为什么喜欢手语？"},
    {"input": "我 手语 喜欢 为什么", "output": "我为什么喜欢手语？"},
    {"input": "谢谢 你 手语 会", "output": "谢谢你，你会手语吗？"},
    {"input": "对不起 我 手语 会", "output": "对不起，我不会手语。"},
    {"input": "没关系 你 会 手语", "output": "没关系，你会手语。"},
    {"input": "谢谢 大家 你好", "output": "谢谢大家，你们好！"},
    {"input": "你好 我 对不起", "output": "你好，对不起。"},
    {"input": "为什么 对不起 我", "output": "为什么我对不起你？"},
    {"input": "手语 我 会 谢谢", "output": "我会手语，谢谢。"},
    {"input": "大家 手语 喜欢 谢谢", "output": "大家喜欢手语，谢谢。"},
    {"input": "为什么 对不起 大家", "output": "为什么对不起大家？"},
    {"input": "没关系 大家 喜欢 你", "output": "没关系，大家喜欢你。"},
    {"input": "谁 对不起 你", "output": "谁对不起你？"},
    {"input": "谁 谢谢 我", "output": "谁谢谢我？"},
    {"input": "没关系 谢谢 你", "output": "没关系，谢谢你。"},
    {"input": "我 喜欢 你 没关系", "output": "我喜欢你，没关系。"},
    {"input": "你 喜欢 手语 为什么", "output": "你为什么喜欢手语？"},
    {"input": "我 会 手语 你 会 手语", "output": "我会手语，你会手语吗？"},
    {"input": "对不起 我 喜欢 你", "output": "对不起，我喜欢你。"},
    {"input": "谢谢 喜欢 我 你", "output": "谢谢你喜欢我。"},
    {"input": "大家 好 你好", "output": "大家好，你好！"},
    {"input": "对不起 大家 我 喜欢 你", "output": "对不起大家，我喜欢你。"},
    {"input": "我 喜欢 手语 大家", "output": "我喜欢手语，大家呢？"},
    {"input": "你 会 手语 谢谢", "output": "你会手语，谢谢。"},
    {"input": "为什么 喜欢 我 大家", "output": "为什么大家喜欢我？"},
    {"input": "谁 会 喜欢 我", "output": "谁会喜欢我？"},
    {"input": "你好 手语 大家 会", "output": "你好，大家都会手语。"},
    {"input": "谢谢 你 喜欢 手语", "output": "谢谢你喜欢手语。"},
    {"input": "没关系 我 会 手语", "output": "没关系，我会手语。"},
    {"input": "为什么 喜欢 你", "output": "为什么喜欢你？"},
    {"input": "我 会 手语 谢谢 大家", "output": "我会手语，谢谢大家。"},
    {"input": "你 我 喜欢 手语 会", "output": "我喜欢你，我会手语。"},
    {"input": "手语 喜欢 你 我 谢谢", "output": "你也喜欢手语，我谢谢你。"},
    {"input": "为什么 你 对不起 我", "output": "你为什么对不起我？"},
    {"input": "没关系 没关系", "output": "没关系，没关系的。"},
    {"input": "谁 喜欢 我 为什么", "output": "谁喜欢我，为什么？"},
    {"input": "手语 会 手语 喜欢", "output": "会手语，喜欢手语。"},
    {"input": "你 好 谢谢 你 喜欢", "output": "你好，谢谢你的喜欢。"},
    {"input": "对不起 你 喜欢 我 没关系", "output": "对不起，你喜欢我，没关系。"},
    {"input": "谢谢 大家 喜欢 手语", "output": "谢谢大家喜欢手语。"},
    {"input": "我 喜欢 我 手语", "output": "我喜欢手语。"},
    {"input": "你 对不起 大家", "output": "你对不起大家。"},
    {"input": "会 大家 手语", "output": "大家会手语。"},
    {"input": "你好 谢谢 大家", "output": "你好，谢谢大家。"},
    {"input": "我 谢谢 大家 喜欢", "output": "我谢谢大家的喜欢。"},
    {"input": "谁 为什么 喜欢 你", "output": "谁为什么喜欢你？"},
    {"input": "为什么 谁 喜欢 你", "output": "为什么有人喜欢你？"},
    {"input": "没关系 我 喜欢 手语", "output": "没关系，我喜欢手语。"},
    {"input": "你好 谁 会 手语", "output": "你好，谁会手语？"},
    {"input": "对不起 谢谢 你", "output": "对不起，谢谢你。"},
    {"input": "没关系 你 对不起", "output": "没关系，你不用说对不起。"},
    {"input": "手语 你 我 喜欢", "output": "我喜欢手语，你喜欢吗？"}
]
